Workbook

Sheet MBF
A3: Detailed Module Concept - MSc Digital Business Administration
A4: MBF - Management & Organizational Foundations (6 ECTS)
A5: The detailed module concept serves as a comprehensive blueprint for structuring a module over the course of a semester. It defines the key learning goals, ensuring clear educational outcomes for students. It outlines the main content areas, providing a structured framework for effective knowledge delivery. Additionally, it specifies the responsibilities of lecturers, assigning which lecturer is responsible for delivering content in each learning cycle or on-campus session. The concept also includes the assignment structure, detailing assessments and learning activities for each phase of the module. This ensures consistency and alignment with course objectives.
A10: Explanation: | C10: Please describe the key learning goals in each LC and On-Campus session | D10: Please write a short summary of the main content in each LC and On-Campus session in bullet points | E10: Which didactic methods and teaching tools are used in each LC and On-Campus session? | F10: Please describe the assignment (if applicable) in bullet points | G10: Please choose assignment type from the drop-down menu | H10: Please select the grading percentage from the drop-down menu | I10: Please specify the lecturer responsible for each LC and On-Campus session
A12: Structural Elements | B12: Dates | C12: Learning Goals | D12: Main Content (bullet points) | E12: Didactics & Tools | F12: Description Assignment (bullet points) | G12: Assignment Type (drop down) | H12: Grading Percentage (drop down) | I12: Lecturer | J12: Comments
A13: CW 40 On-Campus 1 | B13: 01.10.-03.10. | C13: - Studierende verstehen Grundfunktionen des Managements | D13: - Planen, Organisieren, Führen, Kontrollieren | E13: - Vorlesung - Diskussion | I13: Prof. Aeschbacher
A14: CW 39-40 Learning Cycle 1 | B14: 21.09.-04.10. | C14: - Studierende können Organisationsformen vergleichen | D14: - Funktionale vs. divisionale Organisation - Matrixorganisation | E14: - Fallstudie | I14: Prof. Aeschbacher
A15: CW 41-42 Learning Cycle 2 | B15: 05.10.-18.10. | C15: - Studierende können ein Geschäftsmodell strukturiert beschreiben | D15: - Business Model Canvas - Value Proposition Design | E15: - Video-Tutorial - Vorlage zum Selbstausfüllen | F15: - Ausgefülltes Canvas für ein selbst gewähltes Unternehmen | G15: Graded | H15: 0.2 | I15: Prof. Aeschbacher
A16: CW 43 On-Campus 2 | B16: 22.10.-24.10. | C16: - Studierende können ihr Canvas im Plenum verteidigen | D16: - Präsentation der Canvas-Entwürfe - Peer-Feedback | E16: - Kurzpräsentationen | I16: Prof. Aeschbacher
A17: CW 44-45 Learning Cycle 3 | B17: 26.10.-08.11. | C17: - Studierende kennen Grundmodelle der Organisationskultur | D17: - Kulturmodelle nach Schein - Artefakte, Werte, Grundannahmen | E17: - Lesetext | I17: Prof. Aeschbacher
A18: CW 46-47 Learning Cycle 4 | B18: 09.11.-22.11. | C18: - Studierende können Stakeholder eines Unternehmens systematisch erfassen | D18: - Stakeholder-Mapping | E18: - Gruppenarbeit | F18: - Stakeholder-Map für ein Fallbeispiel | G18: Pass/Fail | H18: 0 | I18: Prof. Aeschbacher
A19: CW 48 On-Campus 3 | B19: 26.11.-28.11. | C19: - Studierende können Managemententscheidungen kritisch reflektieren | D19: - Entscheidungsfindung unter Unsicherheit | E19: - Fallstudie - Diskussion | I19: Prof. Aeschbacher
A20: CW 49-50 Learning Cycle 5 | B20: 30.11.-13.12. | C20: - Studierende kennen zentrale Managementtheorien im Überblick | D20: - Klassische vs. moderne Managementtheorien | E20: - Lesetext | I20: Prof. Aeschbacher
A21: CW 50-51 Learning Cycle 6 | B21: 07.12.-20.12. | C21: - Studierende können ein Organisationskonzept ausarbeiten | D21: - Finalisierung Organisationskonzept | E21: - Selbststudium | F21: - Organisationskonzept-Papier (max. 5 Seiten) | G21: Graded | H21: 0.3 | I21: Prof. Aeschbacher
A22: CW 51 On-Campus 4 | B22: 17.12.-19.12. | C22: - Studierende können ihr Organisationskonzept präsentieren | D22: - Abschlusspräsentationen | E22: - Gruppenpräsentationen | F22: - Abschlusspräsentation (10 Min.) | G22: Graded | H22: 0.5 | I22: Prof. Aeschbacher
A24: Additional Written Exams, Group Presentations, Reports | B24: After last On-Campus

Sheet FAC
A3: Detailed Module Concept - MSc Digital Business Administration
A4: FAC - Financial Accounting Basics (6 ECTS)
A5: The detailed module concept serves as a comprehensive blueprint for structuring a module over the course of a semester. It defines the key learning goals, ensuring clear educational outcomes for students. It outlines the main content areas, providing a structured framework for effective knowledge delivery. Additionally, it specifies the responsibilities of lecturers, assigning which lecturer is responsible for delivering content in each learning cycle or on-campus session. The concept also includes the assignment structure, detailing assessments and learning activities for each phase of the module. This ensures consistency and alignment with course objectives.
A10: Explanation: | C10: Please describe the key learning goals in each LC and On-Campus session | D10: Please write a short summary of the main content in each LC and On-Campus session in bullet points | E10: Which didactic methods and teaching tools are used in each LC and On-Campus session? | F10: Please describe the assignment (if applicable) in bullet points | G10: Please choose assignment type from the drop-down menu | H10: Please select the grading percentage from the drop-down menu | I10: Please specify the lecturer responsible for each LC and On-Campus session
A12: Structural Elements | B12: Dates | C12: Learning Goals | D12: Main Content (bullet points) | E12: Didactics & Tools | F12: Description Assignment (bullet points) | G12: Assignment Type (drop down) | H12: Grading Percentage (drop down) | I12: Lecturer | J12: Comments
A13: CW 40 On-Campus 1 | B13: 01.10.-03.10. | C13: - Studierende verstehen Aufbau und Zweck der Bilanz | D13: - Aktiven, Passiven, Eigenkapital | E13: - Vorlesung | I13: Prof. Egger
A14: CW 39-40 Learning Cycle 1 | B14: 21.09.-04.10. | C14: - Studierende können einfache Buchungssätze bilden | D14: - Doppelte Buchführung - Grundbuchungen | E14: - Übungsaufgaben | F14: - Buchungsübung anhand eines Fallbeispiels | G14: Pass/Fail | H14: 0 | I14: Prof. Egger
A15: CW 41-42 Learning Cycle 2 | B15: 05.10.-18.10. | C15: - Studierende verstehen die Erfolgsrechnung | D15: - Aufwand, Ertrag, Gewinn | E15: - Übungsaufgaben | I15: Prof. Egger
A16: CW 43 On-Campus 2 | B16: 22.10.-24.10. | C16: - Studierende können ihre Buchungsübungen im Plenum diskutieren | D16: - Besprechung Übungsfälle | E16: - Plenumsdiskussion | I16: Prof. Egger
A17: CW 44-45 Learning Cycle 3 | B17: 26.10.-08.11. | C17: - Studierende können zentrale Finanzkennzahlen berechnen | D17: - Liquiditätsgrade - Rentabilitätskennzahlen | E17: - Übungsdatensatz | I17: Prof. Egger
A18: CW 46-47 Learning Cycle 4 | B18: 09.11.-22.11. | C18: - Studierende können eine Jahresrechnung analysieren | D18: - Kennzahlenanalyse eines Fallunternehmens | E18: - Fallstudie | F18: - Kennzahlenanalyse-Bericht | G18: Graded | H18: 0.25 | I18: Prof. Egger
A19: CW 48 On-Campus 3 | B19: 26.11.-28.11. | C19: - Studierende kennen Grundzüge der Kostenrechnung | D19: - Fixkosten, variable Kosten, Deckungsbeitrag | E19: - Lesetext | I19: Prof. Egger
A20: CW 49-50 Learning Cycle 5 | B20: 30.11.-13.12. | C20: - Studierende können eine Break-Even-Analyse durchführen | D20: - Break-Even-Point - Szenariorechnung | E20: - Übungsaufgaben | I20: Prof. Egger
A21: CW 50-51 Learning Cycle 6 | B21: 07.12.-20.12. | C21: - Studierende können ein einfaches Budget erstellen | D21: - Budgetierung Grundlagen | E21: - Selbststudium | F21: - Budgetplan für ein Fallbeispiel | G21: Graded | H21: 0.25 | I21: Prof. Egger
A22: CW 51 On-Campus 4 | B22: 17.12.-19.12. | C22: - Studierende können ihre Finanzanalyse präsentieren | D22: - Abschlusspräsentationen | E22: - Gruppenpräsentationen | F22: - Abschlusspräsentation (10 Min.) | G22: Graded | H22: 0.5 | I22: Prof. Egger
A24: Additional Written Exams, Group Presentations, Reports | B24: After last On-Campus

Sheet MEC
A3: Detailed Module Concept - MSc Digital Business Administration
A4: MEC - Managerial Economics (3 ECTS)
A5: The detailed module concept serves as a comprehensive blueprint for structuring a module over the course of a semester. It defines the key learning goals, ensuring clear educational outcomes for students. It outlines the main content areas, providing a structured framework for effective knowledge delivery. Additionally, it specifies the responsibilities of lecturers, assigning which lecturer is responsible for delivering content in each learning cycle or on-campus session. The concept also includes the assignment structure, detailing assessments and learning activities for each phase of the module. This ensures consistency and alignment with course objectives.
A10: Explanation: | C10: Please describe the key learning goals in each LC and On-Campus session | D10: Please write a short summary of the main content in each LC and On-Campus session in bullet points | E10: Which didactic methods and teaching tools are used in each LC and On-Campus session? | F10: Please describe the assignment (if applicable) in bullet points | G10: Please choose assignment type from the drop-down menu | H10: Please select the grading percentage from the drop-down menu | I10: Please specify the lecturer responsible for each LC and On-Campus session
A12: Structural Elements | B12: Dates | C12: Learning Goals | D12: Main Content (bullet points) | E12: Didactics & Tools | F12: Description Assignment (bullet points) | G12: Assignment Type (drop down) | H12: Grading Percentage (drop down) | I12: Lecturer | J12: Comments
A13: CW 40 On-Campus 1 | B13: 01.10.-03.10. | C13: - Studierende kennen Grundprinzipien von Angebot und Nachfrage | D13: - Marktmechanismen | E13: - Vorlesung | I13: Prof. Baumann
A14: CW 39-40 Learning Cycle 1 | B14: 21.09.-04.10. | D14: - Fallbeispiel Preiselastizität | E14: - Diskussion | I14: Prof. Baumann
A15: CW 41-42 Learning Cycle 2 | B15: 05.10.-18.10. | C15: - Studierende können Marktstrukturen unterscheiden | D15: - Monopol, Oligopol, vollständige Konkurrenz | E15: - Fallstudie | F15: - Kurzanalyse einer Marktstruktur | G15: Pass/Fail | H15: 0 | I15: Prof. Baumann
A16: CW 43 On-Campus 2 | B16: 22.10.-24.10.
A17: CW 44-45 Learning Cycle 3 | B17: 26.10.-08.11. | C17: - Studierende kennen Grundlagen der Preisstrategie | D17: - Preisdifferenzierung | E17: - Lesetext | I17: Prof. Baumann
A18: CW 46-47 Learning Cycle 4 | B18: 09.11.-22.11.
A19: CW 48 On-Campus 3 | B19: 26.11.-28.11. | C19: - Studierende können ein einfaches Pricing-Modell anwenden | D19: - Pricing-Übung | E19: - Gruppenarbeit | I19: Prof. Baumann
A20: CW 49-50 Learning Cycle 5 | B20: 30.11.-13.12.
A21: CW 50-51 Learning Cycle 6 | B21: 07.12.-20.12. | C21: - Studierende können eine Preisstrategie ausarbeiten | D21: - Finalisierung Preisstrategie-Papier | E21: - Selbststudium | F21: - Preisstrategie-Papier (max. 3 Seiten) | G21: Graded | H21: 0.5 | I21: Prof. Baumann
A22: CW 51 On-Campus 4 | B22: 17.12.-19.12. | D22: - Abschlusspräsentationen | E22: - Kurzpräsentationen | F22: - Präsentation (7 Min.) | G22: Graded | H22: 0.5 | I22: Prof. Baumann
A24: Additional Written Exams, Group Presentations, Reports | B24: After last On-Campus

Sheet BCM
A3: Detailed Module Concept - MSc Digital Business Administration
A4: BCM - Business Communication (3 ECTS)
A5: The detailed module concept serves as a comprehensive blueprint for structuring a module over the course of a semester. It defines the key learning goals, ensuring clear educational outcomes for students. It outlines the main content areas, providing a structured framework for effective knowledge delivery. Additionally, it specifies the responsibilities of lecturers, assigning which lecturer is responsible for delivering content in each learning cycle or on-campus session. The concept also includes the assignment structure, detailing assessments and learning activities for each phase of the module. This ensures consistency and alignment with course objectives.
A10: Explanation: | C10: Please describe the key learning goals in each LC and On-Campus session | D10: Please write a short summary of the main content in each LC and On-Campus session in bullet points | E10: Which didactic methods and teaching tools are used in each LC and On-Campus session? | F10: Please describe the assignment (if applicable) in bullet points | G10: Please choose assignment type from the drop-down menu | H10: Please select the grading percentage from the drop-down menu | I10: Please specify the lecturer responsible for each LC and On-Campus session
A12: Structural Elements | B12: Dates | C12: Learning Goals | D12: Main Content (bullet points) | E12: Didactics & Tools | F12: Description Assignment (bullet points) | G12: Assignment Type (drop down) | H12: Grading Percentage (drop down) | I12: Lecturer | J12: Comments
A13: CW 40 On-Campus 1 | B13: 01.10.-03.10. | C13: - Studierende kennen Grundprinzipien wirkungsvoller Geschäftskommunikation | D13: - Zielgruppenorientierte Kommunikation | E13: - Vorlesung | I13: Prof. Chapuis
A14: CW 39-40 Learning Cycle 1 | B14: 21.09.-04.10. | D14: - Kennenlern-Übung - Erwartungsmanagement | E14: - Gruppenübung | I14: Prof. Chapuis
A15: CW 41-42 Learning Cycle 2 | B15: 05.10.-18.10. | C15: - Studierende können Feedbackgespräche strukturiert führen | D15: - Feedbackmodelle - Aktives Zuhören | E15: - Rollenspiel | F15: - Reflexionstext zu einem Feedbackgespräch | G15: Pass/Fail | H15: 0 | I15: Prof. Chapuis
A16: CW 43 On-Campus 2 | B16: 22.10.-24.10.
A17: CW 44-45 Learning Cycle 3 | B17: 26.10.-08.11. | C17: - Studierende kennen Grundlagen professioneller Präsentationstechnik | D17: - Aufbau überzeugender Präsentationen | E17: - Lesetext | I17: Prof. Chapuis
A18: CW 46-47 Learning Cycle 4 | B18: 09.11.-22.11.
A19: CW 48 On-Campus 3 | B19: 26.11.-28.11. | C19: - Studierende können eine Kurzpräsentation vorbereiten | D19: - Präsentationsübung | E19: - Coaching in Kleingruppen | I19: Prof. Chapuis
A20: CW 49-50 Learning Cycle 5 | B20: 30.11.-13.12.
A21: CW 50-51 Learning Cycle 6 | B21: 07.12.-20.12. | C21: - Studierende können eine überzeugende Geschäftspräsentation ausarbeiten | D21: - Finalisierung Präsentation | E21: - Selbststudium | F21: - Geschäftspräsentation (max. 8 Folien) | G21: Graded | H21: 0.5 | I21: Prof. Chapuis
A22: CW 51 On-Campus 4 | B22: 17.12.-19.12. | D22: - Abschlusspräsentationen mit Peer-Feedback | E22: - Kurzpräsentationen | F22: - Präsentation (7 Min.) | G22: Graded | H22: 0.5 | I22: Prof. Chapuis
A24: Additional Written Exams, Group Presentations, Reports | B24: After last On-Campus

Sheet Module Coordination
A2: Module Coordination
A3: Overview of Main Content per Learning Cycle across all modules of the semester - used to spot unintended overlaps and coordinate workload.
A5: Structural Elements | B5: Dates | C5: MBF - Management & Organizational Foundations | D5: FAC - Financial Accounting Basics | E5: MEC - Managerial Economics | F5: BCM - Business Communication
A6: CW 40 On-Campus 1 | B6: 01.10.-03.10. | C6: =MBF!D13 -> - Planen, Organisieren, Führen, Kontrollieren | D6: =FAC!D13 -> - Aktiven, Passiven, Eigenkapital | E6: =MEC!D13 -> - Marktmechanismen | F6: =BCM!D13 -> - Zielgruppenorientierte Kommunikation
A7: CW 39-40 Learning Cycle 1 | B7: 21.09.-04.10. | C7: =MBF!D14 -> - Funktionale vs. divisionale Organisation - Matrixorganisation | D7: =FAC!D14 -> - Doppelte Buchführung - Grundbuchungen | E7: =MEC!D14 -> - Fallbeispiel Preiselastizität | F7: =BCM!D14 -> - Kennenlern-Übung - Erwartungsmanagement
A8: CW 41-42 Learning Cycle 2 | B8: 05.10.-18.10. | C8: =MBF!D15 -> - Business Model Canvas - Value Proposition Design | D8: =FAC!D15 -> - Aufwand, Ertrag, Gewinn | E8: =MEC!D15 -> - Monopol, Oligopol, vollständige Konkurrenz | F8: =BCM!D15 -> - Feedbackmodelle - Aktives Zuhören
A9: CW 43 On-Campus 2 | B9: 22.10.-24.10. | C9: =MBF!D16 -> - Präsentation der Canvas-Entwürfe - Peer-Feedback | D9: =FAC!D16 -> - Besprechung Übungsfälle | E9: =MEC!D16 -> 0 | F9: =BCM!D16 -> 0
A10: CW 44-45 Learning Cycle 3 | B10: 26.10.-08.11. | C10: =MBF!D17 -> - Kulturmodelle nach Schein - Artefakte, Werte, Grundannahmen | D10: =FAC!D17 -> - Liquiditätsgrade - Rentabilitätskennzahlen | E10: =MEC!D17 -> - Preisdifferenzierung | F10: =BCM!D17 -> - Aufbau überzeugender Präsentationen
A11: CW 46-47 Learning Cycle 4 | B11: 09.11.-22.11. | C11: =MBF!D18 -> - Stakeholder-Mapping | D11: =FAC!D18 -> - Kennzahlenanalyse eines Fallunternehmens | E11: =MEC!D18 -> 0 | F11: =BCM!D18 -> 0
A12: CW 48 On-Campus 3 | B12: 26.11.-28.11. | C12: =MBF!D19 -> - Entscheidungsfindung unter Unsicherheit | D12: =FAC!D19 -> - Fixkosten, variable Kosten, Deckungsbeitrag | E12: =MEC!D19 -> - Pricing-Übung | F12: =BCM!D19 -> - Präsentationsübung
A13: CW 49-50 Learning Cycle 5 | B13: 30.11.-13.12. | C13: =MBF!D20 -> - Klassische vs. moderne Managementtheorien | D13: =FAC!D20 -> - Break-Even-Point - Szenariorechnung | E13: =MEC!D20 -> 0 | F13: =BCM!D20 -> 0
A14: CW 50-51 Learning Cycle 6 | B14: 07.12.-20.12. | C14: =MBF!D21 -> - Finalisierung Organisationskonzept | D14: =FAC!D21 -> - Budgetierung Grundlagen | E14: =MEC!D21 -> - Finalisierung Preisstrategie-Papier | F14: =BCM!D21 -> - Finalisierung Präsentation
A15: CW 51 On-Campus 4 | B15: 17.12.-19.12. | C15: =MBF!D22 -> - Abschlusspräsentationen | D15: =FAC!D22 -> - Abschlusspräsentationen | E15: =MEC!D22 -> - Abschlusspräsentationen | F15: =BCM!D22 -> - Abschlusspräsentationen mit Peer-Feedback
A17: Total ECTS this semester | C17: =SUM(C18:F18) -> 18
C18: 6 | D18: 6 | E18: 3 | F18: 3

Sheet Parameters
A1: Assignment Percentage | C1: Assignment Type
A2: 0 | C2: Graded
A3: 0.05 | C3: Pass/Fail
A4: 0.1 | C4: Non-graded
A5: 0.15
A6: 0.2
A7: 0.25
A8: 0.3
A9: 0.35
A10: 0.4
A11: 0.45
A12: 0.5
A13: 0.55
A14: 0.6
A15: 0.65
A16: 0.7
... A22: 1
